deep_b_spline_approximation/BSpline.py
deep_b_spline_approximation/__init__.py
deep_b_spline_approximation/__main__.py
deep_b_spline_approximation/deep_b_spline_approximation.py
deep_b_spline_approximation/directedHausdorff.py
deep_b_spline_approximation/evalmodel.py
deep_b_spline_approximation/kpn.py
deep_b_spline_approximation/loadfromtxt.py
deep_b_spline_approximation/ppn.py
deep_b_spline_approximation/preprocessing.py
deep_b_spline_approximation/resumetraining.py
deep_b_spline_approximation/training.py
deep_b_spline_approximation-0.3.7.dist-info/LICENSE
deep_b_spline_approximation-0.3.7.dist-info/METADATA
deep_b_spline_approximation-0.3.7.dist-info/WHEEL
deep_b_spline_approximation-0.3.7.dist-info/top_level.txt
deep_b_spline_approximation-0.3.7.dist-info/RECORD
