Metadata-Version: 2.1
Name: deep-b-spline-approximation
Version: 0.3.7
Summary: A python package for bspline curve approximation using deep learning
Home-page: https://github.com/t-ceccarini/deep-b-spline-approximation
Author: Tommaso Ceccarini
Author-email: <tceccarini93@gmail.com>
License: UNKNOWN
Download-URL: https://github.com/t-ceccarini/deep-b-spline-approximation/archive/refs/tags/v_0.3.7.tar.gz
Keywords: python,deep learning,mlp,cnn,cagd,bspline,bezier
Platform: UNKNOWN
Classifier: Development Status :: 1 - Planning
Classifier: Intended Audience :: Developers
Classifier: Programming Language :: Python :: 3.5
Classifier: Programming Language :: Python :: 3.6
Classifier: Programming Language :: Python :: 3.7
Classifier: Programming Language :: Python :: 3.8
Classifier: Programming Language :: Python :: 3.9
Classifier: Operating System :: Unix
Classifier: Operating System :: MacOS :: MacOS X
Classifier: Operating System :: Microsoft :: Windows
License-File: LICENSE
Requires-Dist: torch
Requires-Dist: prettytable
Requires-Dist: numpy
Requires-Dist: scipy
Requires-Dist: matplotlib
